pantsbuild.pants.contrib.jax_ws-1.28.0-py3.6-nspkg.pth
pants/contrib/jax_ws/__init__.py
pants/contrib/jax_ws/register.py
pants/contrib/jax_ws/target_types.py
pants/contrib/jax_ws/targets/__init__.py
pants/contrib/jax_ws/targets/jax_ws_library.py
pants/contrib/jax_ws/tasks/__init__.py
pants/contrib/jax_ws/tasks/jax_ws_gen.py
pantsbuild.pants.contrib.jax_ws-1.28.0.dist-info/METADATA
pantsbuild.pants.contrib.jax_ws-1.28.0.dist-info/WHEEL
pantsbuild.pants.contrib.jax_ws-1.28.0.dist-info/entry_points.txt
pantsbuild.pants.contrib.jax_ws-1.28.0.dist-info/namespace_packages.txt
pantsbuild.pants.contrib.jax_ws-1.28.0.dist-info/top_level.txt
pantsbuild.pants.contrib.jax_ws-1.28.0.dist-info/zip-safe
pantsbuild.pants.contrib.jax_ws-1.28.0.dist-info/RECORD
